llmcosts/__init__.py
llmcosts/client.py
llmcosts/events.py
llmcosts/exceptions.py
llmcosts/models.py
llmcosts/thresholds.py
llmcosts/tracker/__init__.py
llmcosts/tracker/anthropic_handler.py
llmcosts/tracker/base.py
llmcosts/tracker/bedrock_handler.py
llmcosts/tracker/frameworks.py
llmcosts/tracker/gemini_handler.py
llmcosts/tracker/generic_handler.py
llmcosts/tracker/openai_handler.py
llmcosts/tracker/providers.py
llmcosts/tracker/proxy.py
llmcosts/tracker/py.typed
llmcosts/tracker/registry.py
llmcosts/tracker/usage_delivery.py
llmcosts/tracker/callbacks/__init__.py
llmcosts/tracker/callbacks/sqlite_callback.py
llmcosts/tracker/callbacks/text_callback.py
llmcosts-0.2.6.dist-info/licenses/LICENSE
llmcosts-0.2.6.dist-info/METADATA
llmcosts-0.2.6.dist-info/WHEEL
llmcosts-0.2.6.dist-info/top_level.txt
llmcosts-0.2.6.dist-info/RECORD
