Metadata-Version: 2.4
Name: llmcosts
Version: 0.2.6
Summary: A generic, provider-agnostic SDK wrapper that intercepts LLM API responses and extracts usage information for cost tracking with structured payload formatting.
Author-email: Keyton Weissinger <keyton@llmcosts.com>
Maintainer-email: Keyton Weissinger <keyton@llmcosts.com>
License-Expression: Apache-2.0
Project-URL: Homepage, https://github.com/llmcosts/llmcosts-python
Project-URL: Bug Reports, https://github.com/llmcosts/llmcosts-python/issues
Project-URL: Source, https://github.com/llmcosts/llmcosts-python
Project-URL: Documentation, https://github.com/llmcosts/llmcosts-python#readme
Keywords: llm,ai,cost-tracking,openai,anthropic,gemini,bedrock,usage-monitoring
Classifier: Development Status :: 5 - Production/Stable
Classifier: Intended Audience :: Developers
Classifier: Operating System :: OS Independent
Classifier: Programming Language :: Python :: 3
Classifier: Programming Language :: Python :: 3.9
Classifier: Programming Language :: Python :: 3.10
Classifier: Programming Language :: Python :: 3.11
Classifier: Programming Language :: Python :: 3.12
Classifier: Topic :: Software Development :: Libraries :: Python Modules
Classifier: Topic :: Scientific/Engineering :: Artificial Intelligence
Classifier: Topic :: System :: Monitoring
Requires-Python: >=3.9
License-File: LICENSE
Requires-Dist: requests>=2.31.0
Requires-Dist: PyJWT>=2.8.0
Requires-Dist: cryptography>=3.4.0
Requires-Dist: environs>=10.0.0
Provides-Extra: openai
Requires-Dist: openai>=1.26.0; extra == "openai"
Provides-Extra: anthropic
Requires-Dist: anthropic>=0.24.0; extra == "anthropic"
Provides-Extra: google
Requires-Dist: google-genai; extra == "google"
Provides-Extra: bedrock
Requires-Dist: boto3>=1.26.0; extra == "bedrock"
Provides-Extra: langchain
Requires-Dist: langchain>=0.1.0; extra == "langchain"
Requires-Dist: langchain-openai>=0.1.0; extra == "langchain"
Provides-Extra: all
Requires-Dist: openai>=1.26.0; extra == "all"
Requires-Dist: anthropic>=0.24.0; extra == "all"
Requires-Dist: google-genai; extra == "all"
Requires-Dist: boto3>=1.26.0; extra == "all"
Requires-Dist: langchain>=0.1.0; extra == "all"
Requires-Dist: langchain-openai>=0.1.0; extra == "all"
Provides-Extra: test
Requires-Dist: pytest>=7.0.0; extra == "test"
Requires-Dist: pytest-cov>=4.0.0; extra == "test"
Requires-Dist: boto3>=1.26.0; extra == "test"
Requires-Dist: langchain>=0.1.0; extra == "test"
Requires-Dist: langchain-openai>=0.1.0; extra == "test"
Provides-Extra: dev
Requires-Dist: pytest>=7.0.0; extra == "dev"
Requires-Dist: pytest-cov>=4.0.0; extra == "dev"
Requires-Dist: boto3>=1.26.0; extra == "dev"
Requires-Dist: langchain>=0.1.0; extra == "dev"
Requires-Dist: langchain-openai>=0.1.0; extra == "dev"
Requires-Dist: black>=23.0.0; extra == "dev"
Requires-Dist: isort>=5.12.0; extra == "dev"
Requires-Dist: mypy>=1.0.0; extra == "dev"
Requires-Dist: pre-commit>=3.0.0; extra == "dev"
Dynamic: license-file
